{"_id":{"$oid":"5ce39b0ab88c8e22809dc3be"},"tname":"ExpressTrain(RR55)_BadullaToKandy","tprice":"600","tQuantity":"2"}
{"_id":{"$oid":"5ce39c77b88c8e22809dc3c1"},"tname":"ExpressTrain(RR55)_KandyToBadulla","tprice":"600","tQuantity":"1"}
{"_id":{"$oid":"5ce39cf8b88c8e22809dc3c2"},"tname":"ExpressTrain(RR100)_KandyToMaradana","tprice":"550","tQuantity":"1"}
{"_id":{"$oid":"5ce39d56b88c8e22809dc3c3"},"tname":"ExpressTrain(RR67)_PeradeniyaToBadulla","tprice":"500","tQuantity":"2"}
{"_id":{"$oid":"5ce39dc0b88c8e22809dc3c4"},"tname":"ExpressTrain(RR80)_GalleToMatara","tprice":"300","tQuantity":"4"}
{"_id":{"$oid":"5ce39e1eb88c8e22809dc3c5"},"tname":"ExpressTrain(RR66)_KotuwaToKandy","tprice":"600","tQuantity":"1"}
{"_id":{"$oid":"5ce39e74b88c8e22809dc3c6"},"tname":"ExpressTrain(RR98)_HambanthotaToGalle","tprice":"650","tQuantity":"2"}
{"_id":{"$oid":"5ce39eddb88c8e22809dc3c7"},"tname":"ExpressTrain(RR34)_TrincomaleeToJaffna","tprice":"450","tQuantity":"1"}
